{"nodes": [{"id": 0, "size": 21, "stability:": 19.003809523809533}, {"id": 1, "size": 164, "stability:": 163.00000000000017}, {"id": 2, "size": 187, "stability:": 184.49625668449184}, {"id": 3, "size": 53, "stability:": 35.17962264150945}, {"id": 4, "size": 22, "stability:": 12.854545454545452}, {"id": 5, "size": 10, "stability:": 9.0}, {"id": 6, "size": 8, "stability:": 6.999999999999997}, {"id": 7, "size": 33, "stability:": 30.983030303030304}, {"id": 8, "size": 5, "stability:": 3.0160000000000005}, {"id": 9, "size": 26, "stability:": 18.071538461538466}, {"id": 10, "size": 6, "stability:": 5.000000000000002}, {"id": 11, "size": 3, "stability:": 0.8533333333333335}, {"id": 12, "size": 2, "stability:": 0.9999999999999998}, {"id": 13, "size": 2, "stability:": 0.9999999999999998}, {"id": 14, "size": 30, "stability:": 29.0}], "edges": [{"source": 0, "target": 1, "instability": 0.0}, {"source": 0, "target": 2, "instability": 0.0}, {"source": 0, "target": 3, "instability": 0.010790831687943253}, {"source": 0, "target": 4, "instability": 0.24890452628159093}, {"source": 0, "target": 5, "instability": 0.0}, {"source": 0, "target": 6, "instability": 0.0}, {"source": 0, "target": 7, "instability": 0.0}, {"source": 0, "target": 8, "instability": 0.0}, {"source": 0, "target": 9, "instability": 0.001711841970043652}, {"source": 0, "target": 10, "instability": 0.0}, {"source": 0, "target": 11, "instability": 0.0}, {"source": 0, "target": 12, "instability": 0.0}, {"source": 0, "target": 13, "instability": 0.0}, {"source": 0, "target": 14, "instability": 0.0}, {"source": 1, "target": 2, "instability": 0.0}, {"source": 1, "target": 3, "instability": 0.0}, {"source": 1, "target": 4, "instability": 0.0}, {"source": 1, "target": 5, "instability": 0.0}, {"source": 1, "target": 6, "instability": 0.0}, {"source": 1, "target": 7, "instability": 0.0}, {"source": 1, "target": 8, "instability": 0.0}, {"source": 1, "target": 9, "instability": 0.0}, {"source": 1, "target": 10, "instability": 0.0}, {"source": 1, "target": 11, "instability": 0.0}, {"source": 1, "target": 12, "instability": 0.0}, {"source": 1, "target": 13, "instability": 0.36221540552549664}, {"source": 1, "target": 14, "instability": 0.0}, {"source": 2, "target": 3, "instability": 0.0}, {"source": 2, "target": 4, "instability": 0.007483574624400385}, {"source": 2, "target": 5, "instability": 0.0}, {"source": 2, "target": 6, "instability": 0.0}, {"source": 2, "target": 7, "instability": 0.0}, {"source": 2, "target": 8, "instability": 0.008829944192264336}, {"source": 2, "target": 9, "instability": 0.0}, {"source": 2, "target": 10, "instability": 0.0}, {"source": 2, "target": 11, "instability": 0.0008444006618414983}, {"source": 2, "target": 12, "instability": 0.0}, {"source": 2, "target": 13, "instability": 0.0010341753799900384}, {"source": 2, "target": 14, "instability": 0.0}, {"source": 3, "target": 4, "instability": 0.028113955807556292}, {"source": 3, "target": 5, "instability": 0.0}, {"source": 3, "target": 6, "instability": 0.0}, {"source": 3, "target": 7, "instability": 0.0}, {"source": 3, "target": 8, "instability": 0.0}, {"source": 3, "target": 9, "instability": 9.170984787571902}, {"source": 3, "target": 10, "instability": 0.0}, {"source": 3, "target": 11, "instability": 0.0}, {"source": 3, "target": 12, "instability": 0.0}, {"source": 3, "target": 13, "instability": 0.0}, {"source": 3, "target": 14, "instability": 21.389446789533007}, {"source": 4, "target": 5, "instability": 0.0}, {"source": 4, "target": 6, "instability": 0.0}, {"source": 4, "target": 7, "instability": 6.322281480047188}, {"source": 4, "target": 8, "instability": 0.010488088481701513}, {"source": 4, "target": 9, "instability": 1.5462114765031105}, {"source": 4, "target": 10, "instability": 0.0}, {"source": 4, "target": 11, "instability": 0.0}, {"source": 4, "target": 12, "instability": 0.0}, {"source": 4, "target": 13, "instability": 0.0}, {"source": 4, "target": 14, "instability": 0.0}, {"source": 5, "target": 6, "instability": 0.0}, {"source": 5, "target": 7, "instability": 0.0}, {"source": 5, "target": 8, "instability": 0.0}, {"source": 5, "target": 9, "instability": 0.0}, {"source": 5, "target": 10, "instability": 0.0}, {"source": 5, "target": 11, "instability": 0.0}, {"source": 5, "target": 12, "instability": 0.0}, {"source": 5, "target": 13, "instability": 0.0}, {"source": 5, "target": 14, "instability": 0.0}, {"source": 6, "target": 7, "instability": 0.0}, {"source": 6, "target": 8, "instability": 0.0}, {"source": 6, "target": 9, "instability": 0.0}, {"source": 6, "target": 10, "instability": 0.0}, {"source": 6, "target": 11, "instability": 0.0}, {"source": 6, "target": 12, "instability": 0.0}, {"source": 6, "target": 13, "instability": 0.0}, {"source": 6, "target": 14, "instability": 0.0}, {"source": 7, "target": 8, "instability": 0.0}, {"source": 7, "target": 9, "instability": 0.004438126822992973}, {"source": 7, "target": 10, "instability": 0.0}, {"source": 7, "target": 11, "instability": 0.0}, {"source": 7, "target": 12, "instability": 0.0}, {"source": 7, "target": 13, "instability": 0.0}, {"source": 7, "target": 14, "instability": 0.0}, {"source": 8, "target": 9, "instability": 0.0}, {"source": 8, "target": 10, "instability": 0.0438178046004133}, {"source": 8, "target": 11, "instability": 0.21946905628508698}, {"source": 8, "target": 12, "instability": 0.23400854685246006}, {"source": 8, "target": 13, "instability": 0.7968939703624315}, {"source": 8, "target": 14, "instability": 0.0}, {"source": 9, "target": 10, "instability": 0.0}, {"source": 9, "target": 11, "instability": 0.0}, {"source": 9, "target": 12, "instability": 0.0}, {"source": 9, "target": 13, "instability": 0.0}, {"source": 9, "target": 14, "instability": 0.0}, {"source": 10, "target": 11, "instability": 0.15556349186104051}, {"source": 10, "target": 12, "instability": 0.0}, {"source": 10, "target": 13, "instability": 0.0}, {"source": 10, "target": 14, "instability": 0.0}, {"source": 11, "target": 12, "instability": 0.59604250407724}, {"source": 11, "target": 13, "instability": 0.016329931618554522}, {"source": 11, "target": 14, "instability": 0.0}, {"source": 12, "target": 13, "instability": 0.0}, {"source": 12, "target": 14, "instability": 0.0}, {"source": 13, "target": 14, "instability": 0.0}]}