{"nodes": [{"id": 0, "size": 181, "stability:": 179.12883977900552}, {"id": 1, "size": 168, "stability:": 167.00000000000017}, {"id": 2, "size": 10, "stability:": 7.714}, {"id": 3, "size": 31, "stability:": 22.025806451612905}, {"id": 4, "size": 7, "stability:": 4.765714285714285}, {"id": 5, "size": 41, "stability:": 29.72439024390244}, {"id": 6, "size": 13, "stability:": 10.89846153846154}, {"id": 7, "size": 6, "stability:": 4.133333333333334}, {"id": 8, "size": 19, "stability:": 17.962105263157884}, {"id": 9, "size": 28, "stability:": 22.396428571428565}, {"id": 10, "size": 8, "stability:": 6.767499999999999}, {"id": 11, "size": 15, "stability:": 11.399999999999997}, {"id": 12, "size": 22, "stability:": 19.634545454545446}, {"id": 13, "size": 4, "stability:": 2.2199999999999998}, {"id": 14, "size": 2, "stability:": 0.9999999999999998}, {"id": 15, "size": 2, "stability:": 0.7999999999999999}, {"id": 16, "size": 3, "stability:": 1.5866666666666671}, {"id": 17, "size": 8, "stability:": 3.707499999999999}, {"id": 18, "size": 4, "stability:": 2.965}], "edges": [{"source": 0, "target": 1, "instability": 0.0}, {"source": 0, "target": 2, "instability": 0.0}, {"source": 0, "target": 3, "instability": 0.0}, {"source": 0, "target": 4, "instability": 0.0}, {"source": 0, "target": 5, "instability": 0.0}, {"source": 0, "target": 6, "instability": 0.0}, {"source": 0, "target": 7, "instability": 0.0}, {"source": 0, "target": 8, "instability": 0.0}, {"source": 0, "target": 9, "instability": 0.0}, {"source": 0, "target": 10, "instability": 0.0}, {"source": 0, "target": 11, "instability": 0.0}, {"source": 0, "target": 12, "instability": 0.0}, {"source": 0, "target": 13, "instability": 0.0}, {"source": 0, "target": 14, "instability": 0.0}, {"source": 0, "target": 15, "instability": 0.0}, {"source": 0, "target": 16, "instability": 0.0}, {"source": 0, "target": 17, "instability": 0.0}, {"source": 0, "target": 18, "instability": 0.0}, {"source": 1, "target": 2, "instability": 0.0}, {"source": 1, "target": 3, "instability": 0.0}, {"source": 1, "target": 4, "instability": 0.0}, {"source": 1, "target": 5, "instability": 0.0}, {"source": 1, "target": 6, "instability": 0.0}, {"source": 1, "target": 7, "instability": 0.0}, {"source": 1, "target": 8, "instability": 0.0}, {"source": 1, "target": 9, "instability": 0.0}, {"source": 1, "target": 10, "instability": 0.0}, {"source": 1, "target": 11, "instability": 0.0}, {"source": 1, "target": 12, "instability": 0.0}, {"source": 1, "target": 13, "instability": 0.0}, {"source": 1, "target": 14, "instability": 0.0}, {"source": 1, "target": 15, "instability": 0.0}, {"source": 1, "target": 16, "instability": 0.0}, {"source": 1, "target": 17, "instability": 0.0}, {"source": 1, "target": 18, "instability": 0.0}, {"source": 2, "target": 3, "instability": 0.02328643520412966}, {"source": 2, "target": 4, "instability": 0.0}, {"source": 2, "target": 5, "instability": 0.003457053588273564}, {"source": 2, "target": 6, "instability": 0.005262348115842175}, {"source": 2, "target": 7, "instability": 0.0}, {"source": 2, "target": 8, "instability": 0.0}, {"source": 2, "target": 9, "instability": 0.0}, {"source": 2, "target": 10, "instability": 0.0}, {"source": 2, "target": 11, "instability": 0.009797958971132711}, {"source": 2, "target": 12, "instability": 3.85777161301467}, {"source": 2, "target": 13, "instability": 0.0}, {"source": 2, "target": 14, "instability": 0.0}, {"source": 2, "target": 15, "instability": 0.0}, {"source": 2, "target": 16, "instability": 0.0}, {"source": 2, "target": 17, "instability": 0.0}, {"source": 2, "target": 18, "instability": 0.0}, {"source": 3, "target": 4, "instability": 0.0}, {"source": 3, "target": 5, "instability": 2.1884325751809897}, {"source": 3, "target": 6, "instability": 0.0}, {"source": 3, "target": 7, "instability": 0.0}, {"source": 3, "target": 8, "instability": 0.0}, {"source": 3, "target": 9, "instability": 1.470716031449066}, {"source": 3, "target": 10, "instability": 0.11557011557017337}, {"source": 3, "target": 11, "instability": 0.0009274777915203366}, {"source": 3, "target": 12, "instability": 0.0}, {"source": 3, "target": 13, "instability": 0.0}, {"source": 3, "target": 14, "instability": 0.0}, {"source": 3, "target": 15, "instability": 0.04064004064006096}, {"source": 3, "target": 16, "instability": 0.0}, {"source": 3, "target": 17, "instability": 0.0}, {"source": 3, "target": 18, "instability": 0.0}, {"source": 4, "target": 5, "instability": 0.0}, {"source": 4, "target": 6, "instability": 0.0}, {"source": 4, "target": 7, "instability": 0.0}, {"source": 4, "target": 8, "instability": 0.0}, {"source": 4, "target": 9, "instability": 0.0}, {"source": 4, "target": 10, "instability": 0.0}, {"source": 4, "target": 11, "instability": 0.0}, {"source": 4, "target": 12, "instability": 0.0}, {"source": 4, "target": 13, "instability": 0.4516675452460265}, {"source": 4, "target": 14, "instability": 0.0}, {"source": 4, "target": 15, "instability": 0.0}, {"source": 4, "target": 16, "instability": 2.8804761511150994}, {"source": 4, "target": 17, "instability": 0.004008918628686365}, {"source": 4, "target": 18, "instability": 0.0}, {"source": 5, "target": 6, "instability": 0.0}, {"source": 5, "target": 7, "instability": 0.0}, {"source": 5, "target": 8, "instability": 0.0007165743639000186}, {"source": 5, "target": 9, "instability": 0.0}, {"source": 5, "target": 10, "instability": 0.10049268872811036}, {"source": 5, "target": 11, "instability": 0.9339013370357026}, {"source": 5, "target": 12, "instability": 0.0}, {"source": 5, "target": 13, "instability": 0.0015617376188860608}, {"source": 5, "target": 14, "instability": 0.0}, {"source": 5, "target": 15, "instability": 0.6968229295322815}, {"source": 5, "target": 16, "instability": 0.0}, {"source": 5, "target": 17, "instability": 0.0}, {"source": 5, "target": 18, "instability": 0.0}, {"source": 6, "target": 7, "instability": 0.0}, {"source": 6, "target": 8, "instability": 0.0}, {"source": 6, "target": 9, "instability": 0.0}, {"source": 6, "target": 10, "instability": 0.0}, {"source": 6, "target": 11, "instability": 0.3895664914774515}, {"source": 6, "target": 12, "instability": 0.001773937187967248}, {"source": 6, "target": 13, "instability": 0.04714951667914448}, {"source": 6, "target": 14, "instability": 0.0}, {"source": 6, "target": 15, "instability": 0.0}, {"source": 6, "target": 16, "instability": 0.0}, {"source": 6, "target": 17, "instability": 0.0}, {"source": 6, "target": 18, "instability": 0.0}, {"source": 7, "target": 8, "instability": 0.0}, {"source": 7, "target": 9, "instability": 0.0802377419802878}, {"source": 7, "target": 10, "instability": 0.0}, {"source": 7, "target": 11, "instability": 0.020027758514399738}, {"source": 7, "target": 12, "instability": 0.0}, {"source": 7, "target": 13, "instability": 0.0}, {"source": 7, "target": 14, "instability": 0.1096965511460289}, {"source": 7, "target": 15, "instability": 0.09237604307034014}, {"source": 7, "target": 16, "instability": 0.0}, {"source": 7, "target": 17, "instability": 0.3911548073759715}, {"source": 7, "target": 18, "instability": 0.0}, {"source": 8, "target": 9, "instability": 0.0}, {"source": 8, "target": 10, "instability": 0.0}, {"source": 8, "target": 11, "instability": 0.0029617443887954616}, {"source": 8, "target": 12, "instability": 0.0}, {"source": 8, "target": 13, "instability": 0.0}, {"source": 8, "target": 14, "instability": 0.0}, {"source": 8, "target": 15, "instability": 0.0}, {"source": 8, "target": 16, "instability": 0.0}, {"source": 8, "target": 17, "instability": 0.0}, {"source": 8, "target": 18, "instability": 0.0}, {"source": 9, "target": 10, "instability": 0.0}, {"source": 9, "target": 11, "instability": 0.0}, {"source": 9, "target": 12, "instability": 0.0}, {"source": 9, "target": 13, "instability": 0.0}, {"source": 9, "target": 14, "instability": 0.0}, {"source": 9, "target": 15, "instability": 0.0}, {"source": 9, "target": 16, "instability": 0.0}, {"source": 9, "target": 17, "instability": 0.0}, {"source": 9, "target": 18, "instability": 0.0}, {"source": 10, "target": 11, "instability": 0.0}, {"source": 10, "target": 12, "instability": 0.0}, {"source": 10, "target": 13, "instability": 0.0}, {"source": 10, "target": 14, "instability": 0.0}, {"source": 10, "target": 15, "instability": 0.0}, {"source": 10, "target": 16, "instability": 0.0}, {"source": 10, "target": 17, "instability": 0.0}, {"source": 10, "target": 18, "instability": 0.0}, {"source": 11, "target": 12, "instability": 0.0}, {"source": 11, "target": 13, "instability": 0.8688392639991971}, {"source": 11, "target": 14, "instability": 0.01095445115010332}, {"source": 11, "target": 15, "instability": 0.03286335345030996}, {"source": 11, "target": 16, "instability": 0.0}, {"source": 11, "target": 17, "instability": 0.055685126679691874}, {"source": 11, "target": 18, "instability": 0.0}, {"source": 12, "target": 13, "instability": 0.0}, {"source": 12, "target": 14, "instability": 0.0}, {"source": 12, "target": 15, "instability": 0.0}, {"source": 12, "target": 16, "instability": 0.0}, {"source": 12, "target": 17, "instability": 0.0}, {"source": 12, "target": 18, "instability": 0.0}, {"source": 13, "target": 14, "instability": 0.0}, {"source": 13, "target": 15, "instability": 0.0}, {"source": 13, "target": 16, "instability": 0.0}, {"source": 13, "target": 17, "instability": 0.019445436482630054}, {"source": 13, "target": 18, "instability": 0.05}, {"source": 14, "target": 15, "instability": 0.4899999999999999}, {"source": 14, "target": 16, "instability": 0.0}, {"source": 14, "target": 17, "instability": 0.9249999999999998}, {"source": 14, "target": 18, "instability": 0.0}, {"source": 15, "target": 16, "instability": 0.0}, {"source": 15, "target": 17, "instability": 1.8199999999999994}, {"source": 15, "target": 18, "instability": 0.014142135623730949}, {"source": 16, "target": 17, "instability": 0.012247448713915891}, {"source": 16, "target": 18, "instability": 0.40703193977868624}, {"source": 17, "target": 18, "instability": 0.056568542494923796}]}