{"nodes": [{"id": 0, "size": 7, "stability:": 5.857142857142856}, {"id": 1, "size": 185, "stability:": 182.25135135135162}, {"id": 2, "size": 165, "stability:": 164.00000000000006}, {"id": 3, "size": 4, "stability:": 2.185}, {"id": 4, "size": 13, "stability:": 8.338461538461539}, {"id": 5, "size": 24, "stability:": 21.22083333333334}, {"id": 6, "size": 19, "stability:": 17.696842105263155}, {"id": 7, "size": 16, "stability:": 9.673750000000002}, {"id": 8, "size": 8, "stability:": 6.982499999999996}, {"id": 9, "size": 6, "stability:": 3.8833333333333346}, {"id": 10, "size": 16, "stability:": 12.620000000000001}, {"id": 11, "size": 10, "stability:": 8.812000000000001}, {"id": 12, "size": 22, "stability:": 12.876363636363632}, {"id": 13, "size": 26, "stability:": 18.51923076923077}, {"id": 14, "size": 4, "stability:": 2.675}, {"id": 15, "size": 3, "stability:": 1.7600000000000002}, {"id": 16, "size": 4, "stability:": 1.915}, {"id": 17, "size": 15, "stability:": 12.337333333333332}, {"id": 18, "size": 2, "stability:": 0.9799999999999998}, {"id": 19, "size": 4, "stability:": 1.46}, {"id": 20, "size": 19, "stability:": 17.981052631578944}], "edges": [{"source": 0, "target": 1, "instability": 0.0}, {"source": 0, "target": 2, "instability": 0.0}, {"source": 0, "target": 3, "instability": 0.0}, {"source": 0, "target": 4, "instability": 0.0}, {"source": 0, "target": 5, "instability": 0.0}, {"source": 0, "target": 6, "instability": 0.0}, {"source": 0, "target": 7, "instability": 0.0}, {"source": 0, "target": 8, "instability": 0.0}, {"source": 0, "target": 9, "instability": 0.0}, {"source": 0, "target": 10, "instability": 0.0}, {"source": 0, "target": 11, "instability": 0.0}, {"source": 0, "target": 12, "instability": 0.0}, {"source": 0, "target": 13, "instability": 0.0}, {"source": 0, "target": 14, "instability": 0.003779644730092272}, {"source": 0, "target": 15, "instability": 0.16148123877463438}, {"source": 0, "target": 16, "instability": 0.0}, {"source": 0, "target": 17, "instability": 0.0}, {"source": 0, "target": 18, "instability": 0.0}, {"source": 0, "target": 19, "instability": 0.0}, {"source": 0, "target": 20, "instability": 0.0}, {"source": 1, "target": 2, "instability": 0.0}, {"source": 1, "target": 3, "instability": 0.0959455081832419}, {"source": 1, "target": 4, "instability": 0.0}, {"source": 1, "target": 5, "instability": 0.0}, {"source": 1, "target": 6, "instability": 0.0}, {"source": 1, "target": 7, "instability": 0.0}, {"source": 1, "target": 8, "instability": 0.0}, {"source": 1, "target": 9, "instability": 0.008104053040033468}, {"source": 1, "target": 10, "instability": 0.0}, {"source": 1, "target": 11, "instability": 0.0}, {"source": 1, "target": 12, "instability": 0.00391870710263798}, {"source": 1, "target": 13, "instability": 0.0}, {"source": 1, "target": 14, "instability": 0.007352146220938077}, {"source": 1, "target": 15, "instability": 0.00848952719956018}, {"source": 1, "target": 16, "instability": 0.006616931598844269}, {"source": 1, "target": 17, "instability": 0.0}, {"source": 1, "target": 18, "instability": 0.012996881122750907}, {"source": 1, "target": 19, "instability": 0.04962698699133203}, {"source": 1, "target": 20, "instability": 0.0}, {"source": 2, "target": 3, "instability": 0.0}, {"source": 2, "target": 4, "instability": 0.0}, {"source": 2, "target": 5, "instability": 0.0}, {"source": 2, "target": 6, "instability": 0.0}, {"source": 2, "target": 7, "instability": 0.0}, {"source": 2, "target": 8, "instability": 0.0}, {"source": 2, "target": 9, "instability": 0.0}, {"source": 2, "target": 10, "instability": 0.0}, {"source": 2, "target": 11, "instability": 0.0}, {"source": 2, "target": 12, "instability": 0.0}, {"source": 2, "target": 13, "instability": 0.0}, {"source": 2, "target": 14, "instability": 0.0}, {"source": 2, "target": 15, "instability": 0.0}, {"source": 2, "target": 16, "instability": 0.0}, {"source": 2, "target": 17, "instability": 0.0}, {"source": 2, "target": 18, "instability": 0.0}, {"source": 2, "target": 19, "instability": 0.0}, {"source": 2, "target": 20, "instability": 0.0}, {"source": 3, "target": 4, "instability": 0.0}, {"source": 3, "target": 5, "instability": 0.0010206207261596577}, {"source": 3, "target": 6, "instability": 0.0}, {"source": 3, "target": 7, "instability": 0.0175}, {"source": 3, "target": 8, "instability": 0.0}, {"source": 3, "target": 9, "instability": 0.46744429258112324}, {"source": 3, "target": 10, "instability": 0.0}, {"source": 3, "target": 11, "instability": 0.0}, {"source": 3, "target": 12, "instability": 0.017056057308448832}, {"source": 3, "target": 13, "instability": 0.0}, {"source": 3, "target": 14, "instability": 0.5850000000000001}, {"source": 3, "target": 15, "instability": 0.2540341184434354}, {"source": 3, "target": 16, "instability": 0.26}, {"source": 3, "target": 17, "instability": 0.0}, {"source": 3, "target": 18, "instability": 0.3570889244992065}, {"source": 3, "target": 19, "instability": 1.355}, {"source": 3, "target": 20, "instability": 0.0}, {"source": 4, "target": 5, "instability": 0.0}, {"source": 4, "target": 6, "instability": 0.0012725695259515556}, {"source": 4, "target": 7, "instability": 0.1483823024902488}, {"source": 4, "target": 8, "instability": 0.0}, {"source": 4, "target": 9, "instability": 0.0}, {"source": 4, "target": 10, "instability": 0.02981513554710607}, {"source": 4, "target": 11, "instability": 0.010524696231684352}, {"source": 4, "target": 12, "instability": 0.014191497503737983}, {"source": 4, "target": 13, "instability": 0.04351426345763369}, {"source": 4, "target": 14, "instability": 0.0}, {"source": 4, "target": 15, "instability": 0.0}, {"source": 4, "target": 16, "instability": 0.0}, {"source": 4, "target": 17, "instability": 0.0}, {"source": 4, "target": 18, "instability": 0.0}, {"source": 4, "target": 19, "instability": 0.0}, {"source": 4, "target": 20, "instability": 5.389968227167814}, {"source": 5, "target": 6, "instability": 0.0}, {"source": 5, "target": 7, "instability": 0.0}, {"source": 5, "target": 8, "instability": 0.0}, {"source": 5, "target": 9, "instability": 0.026666666666666672}, {"source": 5, "target": 10, "instability": 0.0}, {"source": 5, "target": 11, "instability": 0.0}, {"source": 5, "target": 12, "instability": 0.0}, {"source": 5, "target": 13, "instability": 2.177342571364672}, {"source": 5, "target": 14, "instability": 0.0}, {"source": 5, "target": 15, "instability": 0.0}, {"source": 5, "target": 16, "instability": 0.0}, {"source": 5, "target": 17, "instability": 0.0}, {"source": 5, "target": 18, "instability": 0.0}, {"source": 5, "target": 19, "instability": 0.0}, {"source": 5, "target": 20, "instability": 0.0}, {"source": 6, "target": 7, "instability": 0.024662191391085386}, {"source": 6, "target": 8, "instability": 0.0}, {"source": 6, "target": 9, "instability": 0.0}, {"source": 6, "target": 10, "instability": 0.007456011350793257}, {"source": 6, "target": 11, "instability": 0.0}, {"source": 6, "target": 12, "instability": 0.0019564639521780737}, {"source": 6, "target": 13, "instability": 0.0}, {"source": 6, "target": 14, "instability": 0.0}, {"source": 6, "target": 15, "instability": 0.0}, {"source": 6, "target": 16, "instability": 0.0}, {"source": 6, "target": 17, "instability": 0.0005923488777590923}, {"source": 6, "target": 18, "instability": 0.0}, {"source": 6, "target": 19, "instability": 0.0}, {"source": 6, "target": 20, "instability": 0.0}, {"source": 7, "target": 8, "instability": 0.03623922253581055}, {"source": 7, "target": 9, "instability": 0.0010206207261596577}, {"source": 7, "target": 10, "instability": 0.505}, {"source": 7, "target": 11, "instability": 0.7020256405573803}, {"source": 7, "target": 12, "instability": 0.014391048354003703}, {"source": 7, "target": 13, "instability": 0.0}, {"source": 7, "target": 14, "instability": 0.125}, {"source": 7, "target": 15, "instability": 0.0}, {"source": 7, "target": 16, "instability": 0.00125}, {"source": 7, "target": 17, "instability": 0.08391463916782736}, {"source": 7, "target": 18, "instability": 0.0017677669529663686}, {"source": 7, "target": 19, "instability": 0.0}, {"source": 7, "target": 20, "instability": 0.0}, {"source": 8, "target": 9, "instability": 0.0}, {"source": 8, "target": 10, "instability": 0.0}, {"source": 8, "target": 11, "instability": 0.0}, {"source": 8, "target": 12, "instability": 0.0422115882408869}, {"source": 8, "target": 13, "instability": 0.0}, {"source": 8, "target": 14, "instability": 0.0}, {"source": 8, "target": 15, "instability": 0.0}, {"source": 8, "target": 16, "instability": 0.0}, {"source": 8, "target": 17, "instability": 0.0}, {"source": 8, "target": 18, "instability": 0.0}, {"source": 8, "target": 19, "instability": 0.0}, {"source": 8, "target": 20, "instability": 0.0}, {"source": 9, "target": 10, "instability": 0.0}, {"source": 9, "target": 11, "instability": 0.0}, {"source": 9, "target": 12, "instability": 0.0}, {"source": 9, "target": 13, "instability": 0.0}, {"source": 9, "target": 14, "instability": 0.0}, {"source": 9, "target": 15, "instability": 0.0}, {"source": 9, "target": 16, "instability": 0.0}, {"source": 9, "target": 17, "instability": 0.0}, {"source": 9, "target": 18, "instability": 0.0}, {"source": 9, "target": 19, "instability": 0.232701525564402}, {"source": 9, "target": 20, "instability": 0.0}, {"source": 10, "target": 11, "instability": 0.0}, {"source": 10, "target": 12, "instability": 9.986321554096792}, {"source": 10, "target": 13, "instability": 0.005883484054145522}, {"source": 10, "target": 14, "instability": 0.0025}, {"source": 10, "target": 15, "instability": 0.0}, {"source": 10, "target": 16, "instability": 0.00125}, {"source": 10, "target": 17, "instability": 0.5364081934497272}, {"source": 10, "target": 18, "instability": 0.0}, {"source": 10, "target": 19, "instability": 0.0}, {"source": 10, "target": 20, "instability": 0.0}, {"source": 11, "target": 12, "instability": 0.0}, {"source": 11, "target": 13, "instability": 0.0}, {"source": 11, "target": 14, "instability": 0.0}, {"source": 11, "target": 15, "instability": 0.0}, {"source": 11, "target": 16, "instability": 0.0}, {"source": 11, "target": 17, "instability": 0.0}, {"source": 11, "target": 18, "instability": 0.0}, {"source": 11, "target": 19, "instability": 0.0}, {"source": 11, "target": 20, "instability": 0.002176428750330035}, {"source": 12, "target": 13, "instability": 3.2132599234522456}, {"source": 12, "target": 14, "instability": 0.004264014327112208}, {"source": 12, "target": 15, "instability": 0.0}, {"source": 12, "target": 16, "instability": 0.07248824356090754}, {"source": 12, "target": 17, "instability": 0.8235208963145175}, {"source": 12, "target": 18, "instability": 0.0}, {"source": 12, "target": 19, "instability": 0.011726039399558574}, {"source": 12, "target": 20, "instability": 0.0}, {"source": 13, "target": 14, "instability": 0.0}, {"source": 13, "target": 15, "instability": 0.0}, {"source": 13, "target": 16, "instability": 0.0}, {"source": 13, "target": 17, "instability": 0.0}, {"source": 13, "target": 18, "instability": 0.0}, {"source": 13, "target": 19, "instability": 0.0}, {"source": 13, "target": 20, "instability": 0.0}, {"source": 14, "target": 15, "instability": 0.1270170592217177}, {"source": 14, "target": 16, "instability": 0.32499999999999996}, {"source": 14, "target": 17, "instability": 0.0}, {"source": 14, "target": 18, "instability": 0.028284271247461898}, {"source": 14, "target": 19, "instability": 0.02}, {"source": 14, "target": 20, "instability": 0.0}, {"source": 15, "target": 16, "instability": 0.16165807537309523}, {"source": 15, "target": 17, "instability": 0.0}, {"source": 15, "target": 18, "instability": 0.0}, {"source": 15, "target": 19, "instability": 0.0}, {"source": 15, "target": 20, "instability": 0.0}, {"source": 16, "target": 17, "instability": 1.222571742952808}, {"source": 16, "target": 18, "instability": 0.07778174593052023}, {"source": 16, "target": 19, "instability": 0.015}, {"source": 16, "target": 20, "instability": 0.0}, {"source": 17, "target": 18, "instability": 0.0}, {"source": 17, "target": 19, "instability": 0.0}, {"source": 17, "target": 20, "instability": 0.0}, {"source": 18, "target": 19, "instability": 0.20506096654409875}, {"source": 18, "target": 20, "instability": 0.0}, {"source": 19, "target": 20, "instability": 0.0}]}